setup.cfg
setup.py
Flask_Filtered_Response.egg-info/PKG-INFO
Flask_Filtered_Response.egg-info/SOURCES.txt
Flask_Filtered_Response.egg-info/dependency_links.txt
Flask_Filtered_Response.egg-info/not-zip-safe
Flask_Filtered_Response.egg-info/requires.txt
Flask_Filtered_Response.egg-info/top_level.txt
flask_filtered_response/__init__.py
tests/__init__.py
tests/test_filtered.py