Metadata-Version: 1.1
Name: Flask-Filtered-Response
Version: 1.0.2
Summary: Add filter capability to JSON responses
Home-page: https://github.com/vrcmarcos/flask-filtered-response
Author: Marcos Cardoso
Author-email: vrcmarcos@gmail.com
License: MIT
Platform: any
Classifier: Environment :: Web Environment
Classifier: Intended Audience :: Developers
Classifier: Operating System :: OS Independent
Classifier: Programming Language :: Python
Classifier: Topic :: Software Development :: Libraries :: Python Modules
